PyVLC/PyVLC.py
PyVLC/__init__.py
pyvlc-1.0.1.dist-info/METADATA
pyvlc-1.0.1.dist-info/WHEEL
pyvlc-1.0.1.dist-info/licenses/LICENSE
pyvlc-1.0.1.dist-info/RECORD
