Metadata-Version: 2.1
Name: PyVLC
Version: 1.0.1
Summary: A python package that utilizes telnetlib3 and asyncio to communicate with VLC Media Player
Project-URL: Homepage, https://github.com/DoofenCorp/PyVLC/
Project-URL: Bug Tracker, https://github.com/DoofenCorp/PyVLC/issues
Author-email: Harshit Bhardwaj <htg4920@gmail.com>
License-File: LICENSE
Classifier: License :: OSI Approved :: MIT License
Classifier: Operating System :: OS Independent
Classifier: Programming Language :: Python :: 3
Requires-Python: >=3.7
